pymem/__init__.py
pymem/macho.py
pymem/process.py
pymem/pymem.py
pymem/types.py
pymem/utils.py
pymem/resources/__init__.py
pymem/resources/vmtypes.py
pymem_osx-1.0.4.dist-info/LICENSE
pymem_osx-1.0.4.dist-info/METADATA
pymem_osx-1.0.4.dist-info/WHEEL
pymem_osx-1.0.4.dist-info/top_level.txt
pymem_osx-1.0.4.dist-info/RECORD
