Metadata-Version: 2.1
Name: pymem-osx
Version: 1.0.4
Summary: A MacOS python library for reading and writing memory of other processes
Home-page: https://github.com/qtkite/pymem-osx
Author: qtkite
License: MIT
Project-URL: Source Code, https://github.com/qtkite/pymem-osx
Classifier: License :: OSI Approved :: MIT License
Classifier: Operating System :: MacOS
Classifier: Programming Language :: Python :: 3
Requires-Python: >=3.8
License-File: LICENSE
